tlquantum/__init__.py
tlquantum/_abs_density_tensor.py
tlquantum/density_tensor.py
tlquantum/maxcut.py
tlquantum/tt_circuit.py
tlquantum/tt_contraction.py
tlquantum/tt_gates.py
tlquantum/tt_operators.py
tlquantum/tt_precontraction.py
tlquantum/tt_state.py
tlquantum/tt_sum.py
tlquantum/tests/__init__.py
tlquantum/tests/test_density_tensor.py
tlquantum/tests/test_maxcut.py
tlquantum/tests/test_tt_circuit.py
tlquantum/tests/test_tt_contraction.py
tlquantum/tests/test_tt_gates.py
tlquantum/tests/test_tt_operators.py
tlquantum/tests/test_tt_precontraction.py
tlquantum/tests/test_tt_state.py
tlquantum/tests/test_tt_sum.py
tensorly_quantum-0.1.0.dist-info/LICENSE
tensorly_quantum-0.1.0.dist-info/METADATA
tensorly_quantum-0.1.0.dist-info/WHEEL
tensorly_quantum-0.1.0.dist-info/top_level.txt
tensorly_quantum-0.1.0.dist-info/RECORD
