Metadata-Version: 2.1
Name: tensorly-quantum
Version: 0.1.0
Summary: Tensor-Based Quantum Machine Learning
Home-page: UNKNOWN
Author: TensorLy-Quantum developers
License: Modified BSD
Platform: UNKNOWN
Classifier: Topic :: Scientific/Engineering
Classifier: License :: OSI Approved :: BSD License
Classifier: Programming Language :: Python :: 3
Requires-Dist: numpy
Requires-Dist: scipy
Requires-Dist: nose
Requires-Dist: tensorly
Requires-Dist: tensorly-torch
Requires-Dist: opt-einsum
